django_treenode-0.23.2.dist-info/licenses/LICENSE.txt
treenode/__init__.py
treenode/admin.py
treenode/cache.py
treenode/debug.py
treenode/exceptions.py
treenode/forms.py
treenode/memory.py
treenode/metadata.py
treenode/models.py
treenode/signals.py
treenode/utils.py
treenode/locale/en/LC_MESSAGES/django.po
treenode/locale/it/LC_MESSAGES/django.po
treenode/static/treenode/css/treenode.css
treenode/static/treenode/js/treenode.js
django_treenode-0.23.2.dist-info/METADATA
django_treenode-0.23.2.dist-info/WHEEL
django_treenode-0.23.2.dist-info/top_level.txt
django_treenode-0.23.2.dist-info/RECORD
